Metadata-Version: 2.1
Name: make-to-batch
Version: 0.2.3
Summary: A Makefile to Batch converter.
Home-page: https://github.com/espositoandrea/Make-to-Batch
Author: Andrea Esposito
Author-email: esposito_andrea99@hotmail.com
License: MIT
Download-URL: https://github.com/espositoandrea/Make-to-Batch/archive/v0.2.3.tar.gz
Keywords: Makefile,Batch,Shell,Windows,Linux,Converter
Platform: UNKNOWN
Classifier: Development Status :: 3 - Alpha
Classifier: Intended Audience :: Developers
Classifier: Topic :: Utilities
Classifier: License :: OSI Approved :: MIT License
Classifier: Programming Language :: Python :: 3
Classifier: Programming Language :: Python :: 3.5
Classifier: Programming Language :: Python :: 3.6
Classifier: Programming Language :: Python :: 3.7
